<?xml version="1.0" ?>
<annotation>
<folder>data</folder>
<filename>frame-00363.jpg</filename>
<path>/Users/jason9075/Documents/Python/my_fcn/data/frame-00363.jpg</path>
<source>
    <database>Unknown</database>
</source>
<size>
    <width>720</width>
    <height>1280</height>
    <depth>3</depth>
</size>

<segmented>0</segmented>
    <object>
    <name>me</name>
    <pose>Unspecified</pose>
    <truncated>0</truncated>
    <difficult>0</difficult>
    <polygon>
			<x1>293</x1>
			<y1>133</y1>
			<x2>243</x2>
			<y2>181</y2>
			<x3>245</x3>
			<y3>229</y3>
			<x4>239</x4>
			<y4>266</y4>
			<x5>262</x5>
			<y5>309</y5>
			<x6>299</x6>
			<y6>325</y6>
			<x7>292</x7>
			<y7>379</y7>
			<x8>264</x8>
			<y8>429</y8>
			<x9>266</x9>
			<y9>524</y9>
			<x10>249</x10>
			<y10>654</y10>
			<x11>237</x11>
			<y11>741</y11>
			<x12>245</x12>
			<y12>937</y12>
			<x13>274</x13>
			<y13>966</y13>
			<x14>286</x14>
			<y14>1087</y14>
			<x15>297</x15>
			<y15>1176</y15>
			<x16>278</x16>
			<y16>1240</y16>
			<x17>197</x17>
			<y17>1277</y17>
			<x18>359</x18>
			<y18>1273</y18>
			<x19>350</x19>
			<y19>1199</y19>
			<x20>354</x20>
			<y20>1108</y20>
			<x21>361</x21>
			<y21>1027</y21>
			<x22>398</x22>
			<y22>1040</y22>
			<x23>501</x23>
			<y23>1093</y23>
			<x24>536</x24>
			<y24>1135</y24>
			<x25>551</x25>
			<y25>1211</y25>
			<x26>569</x26>
			<y26>1273</y26>
			<x27>610</x27>
			<y27>1267</y27>
			<x28>621</x28>
			<y28>1180</y28>
			<x29>604</x29>
			<y29>1093</y29>
			<x30>571</x30>
			<y30>1087</y30>
			<x31>522</x31>
			<y31>1003</y31>
			<x32>451</x32>
			<y32>974</y32>
			<x33>456</x33>
			<y33>852</y33>
			<x34>454</x34>
			<y34>619</y34>
			<x35>454</x35>
			<y35>584</y35>
			<x36>476</x36>
			<y36>427</y36>
			<x37>466</x37>
			<y37>379</y37>
			<x38>433</x38>
			<y38>307</y38>
			<x39>379</x39>
			<y39>299</y39>
			<x40>357</x40>
			<y40>276</y40>
			<x41>383</x41>
			<y41>212</y41>
			<x42>359</x42>
			<y42>167</y42>
		</polygon>
</object>
</annotation>
