<?xml version="1.0" ?>
<annotation>
<folder>data</folder>
<filename>frame-00368.jpg</filename>
<path>/Users/jason9075/Documents/Python/my_fcn/data/frame-00368.jpg</path>
<source>
    <database>Unknown</database>
</source>
<size>
    <width>720</width>
    <height>1280</height>
    <depth>3</depth>
</size>

<segmented>0</segmented>
    <object>
    <name>me</name>
    <pose>Unspecified</pose>
    <truncated>0</truncated>
    <difficult>0</difficult>
    <polygon>
			<x1>213</x1>
			<y1>102</y1>
			<x2>164</x2>
			<y2>138</y2>
			<x3>147</x3>
			<y3>175</y3>
			<x4>151</x4>
			<y4>218</y4>
			<x5>176</x5>
			<y5>280</y5>
			<x6>220</x6>
			<y6>299</y6>
			<x7>234</x7>
			<y7>328</y7>
			<x8>193</x8>
			<y8>365</y8>
			<x9>178</x9>
			<y9>472</y9>
			<x10>162</x10>
			<y10>573</y10>
			<x11>94</x11>
			<y11>687</y11>
			<x12>25</x12>
			<y12>738</y12>
			<x13>36</x13>
			<y13>771</y13>
			<x14>67</x14>
			<y14>763</y14>
			<x15>135</x15>
			<y15>672</y15>
			<x16>178</x16>
			<y16>612</y16>
			<x17>178</x17>
			<y17>763</y17>
			<x18>166</x18>
			<y18>922</y18>
			<x19>156</x19>
			<y19>1017</y19>
			<x20>224</x20>
			<y20>1087</y20>
			<x21>284</x21>
			<y21>1188</y21>
			<x22>271</x22>
			<y22>1238</y22>
			<x23>209</x23>
			<y23>1265</y23>
			<x24>389</x24>
			<y24>1277</y24>
			<x25>356</x25>
			<y25>1207</y25>
			<x26>343</x26>
			<y26>1087</y26>
			<x27>312</x27>
			<y27>963</y27>
			<x28>339</x28>
			<y28>831</y28>
			<x29>376</x29>
			<y29>794</y29>
			<x30>410</x30>
			<y30>784</y30>
			<x31>412</x31>
			<y31>670</y31>
			<x32>426</x32>
			<y32>518</y32>
			<x33>405</x33>
			<y33>420</y33>
			<x34>391</x34>
			<y34>326</y34>
			<x35>345</x35>
			<y35>276</y35>
			<x36>298</x36>
			<y36>278</y36>
			<x37>286</x37>
			<y37>247</y37>
			<x38>298</x38>
			<y38>187</y38>
			<x39>261</x39>
			<y39>125</y39>
		</polygon>
</object>
</annotation>
