<?xml version="1.0" ?>
<annotation>
<folder>data</folder>
<filename>frame-00320.jpg</filename>
<path>/Users/jason9075/Documents/Python/my_fcn/data/frame-00320.jpg</path>
<source>
    <database>Unknown</database>
</source>
<size>
    <width>720</width>
    <height>1280</height>
    <depth>3</depth>
</size>

<segmented>0</segmented>
    <object>
    <name>me</name>
    <pose>Unspecified</pose>
    <truncated>0</truncated>
    <difficult>0</difficult>
    <polygon>
			<x1>441</x1>
			<y1>339</y1>
			<x2>403</x2>
			<y2>348</y2>
			<x3>387</x3>
			<y3>379</y3>
			<x4>393</x4>
			<y4>416</y4>
			<x5>393</x5>
			<y5>445</y5>
			<x6>375</x6>
			<y6>482</y6>
			<x7>346</x7>
			<y7>515</y7>
			<x8>327</x8>
			<y8>552</y8>
			<x9>313</x9>
			<y9>587</y9>
			<x10>300</x10>
			<y10>657</y10>
			<x11>278</x11>
			<y11>734</y11>
			<x12>277</x12>
			<y12>787</y12>
			<x13>300</x13>
			<y13>788</y13>
			<x14>306</x14>
			<y14>721</y14>
			<x15>329</x15>
			<y15>662</y15>
			<x16>348</x16>
			<y16>600</y16>
			<x17>366</x17>
			<y17>593</y17>
			<x18>372</x18>
			<y18>651</y18>
			<x19>364</x19>
			<y19>703</y19>
			<x20>372</x20>
			<y20>765</y20>
			<x21>368</x21>
			<y21>845</y21>
			<x22>372</x22>
			<y22>887</y22>
			<x23>403</x23>
			<y23>901</y23>
			<x24>364</x24>
			<y24>1017</y24>
			<x25>368</x25>
			<y25>1060</y25>
			<x26>420</x26>
			<y26>1072</y26>
			<x27>441</x27>
			<y27>1091</y27>
			<x28>430</x28>
			<y28>1139</y28>
			<x29>439</x29>
			<y29>1159</y29>
			<x30>492</x30>
			<y30>1155</y30>
			<x31>476</x31>
			<y31>1066</y31>
			<x32>469</x32>
			<y32>973</y32>
			<x33>459</x33>
			<y33>907</y33>
			<x34>517</x34>
			<y34>882</y34>
			<x35>509</x35>
			<y35>821</y35>
			<x36>511</x36>
			<y36>705</y36>
			<x37>503</x37>
			<y37>596</y37>
			<x38>525</x38>
			<y38>610</y38>
			<x39>593</x39>
			<y39>691</y39>
			<x40>616</x40>
			<y40>740</y40>
			<x41>635</x41>
			<y41>738</y41>
			<x42>639</x42>
			<y42>691</y42>
			<x43>600</x43>
			<y43>653</y43>
			<x44>565</x44>
			<y44>595</y44>
			<x45>529</x45>
			<y45>534</y45>
			<x46>511</x46>
			<y46>486</y46>
			<x47>470</x47>
			<y47>461</y47>
			<x48>469</x48>
			<y48>420</y48>
			<x49>478</x49>
			<y49>371</y49>
			<x50>453</x50>
			<y50>342</y50>
		</polygon>
</object>
</annotation>
