<?xml version="1.0" ?>
<annotation>
<folder>data</folder>
<filename>frame-00126.jpg</filename>
<path>/Users/jason9075/Documents/Python/my_fcn/data/frame-00126.jpg</path>
<source>
    <database>Unknown</database>
</source>
<size>
    <width>720</width>
    <height>1280</height>
    <depth>3</depth>
</size>

<segmented>0</segmented>
    <object>
    <name>me</name>
    <pose>Unspecified</pose>
    <truncated>0</truncated>
    <difficult>0</difficult>
    <polygon>
			<x1>414</x1>
			<y1>268</y1>
			<x2>461</x2>
			<y2>267</y2>
			<x3>484</x3>
			<y3>334</y3>
			<x4>453</x4>
			<y4>389</y4>
			<x5>490</x5>
			<y5>412</y5>
			<x6>544</x6>
			<y6>521</y6>
			<x7>527</x7>
			<y7>544</y7>
			<x8>548</x8>
			<y8>751</y8>
			<x9>535</x9>
			<y9>810</y9>
			<x10>529</x10>
			<y10>715</y10>
			<x11>498</x11>
			<y11>637</y11>
			<x12>484</x12>
			<y12>528</y12>
			<x13>475</x13>
			<y13>627</y13>
			<x14>504</x14>
			<y14>763</y14>
			<x15>515</x15>
			<y15>856</y15>
			<x16>523</x16>
			<y16>924</y16>
			<x17>455</x17>
			<y17>912</y17>
			<x18>443</x18>
			<y18>1027</y18>
			<x19>414</x19>
			<y19>1128</y19>
			<x20>467</x20>
			<y20>1163</y20>
			<x21>494</x21>
			<y21>1163</y21>
			<x22>473</x22>
			<y22>1199</y22>
			<x23>366</x23>
			<y23>1205</y23>
			<x24>366</x24>
			<y24>1151</y24>
			<x25>379</x25>
			<y25>1027</y25>
			<x26>387</x26>
			<y26>930</y26>
			<x27>341</x27>
			<y27>1029</y27>
			<x28>327</x28>
			<y28>1139</y28>
			<x29>290</x29>
			<y29>1168</y29>
			<x30>269</x30>
			<y30>1137</y30>
			<x31>300</x31>
			<y31>1102</y31>
			<x32>308</x32>
			<y32>988</y32>
			<x33>335</x33>
			<y33>907</y33>
			<x34>337</x34>
			<y34>885</y34>
			<x35>321</x35>
			<y35>866</y35>
			<x36>308</x36>
			<y36>662</y36>
			<x37>304</x37>
			<y37>554</y37>
			<x38>257</x38>
			<y38>660</y38>
			<x39>259</x39>
			<y39>734</y39>
			<x40>230</x40>
			<y40>773</y40>
			<x41>219</x41>
			<y41>718</y41>
			<x42>244</x42>
			<y42>660</y42>
			<x43>277</x43>
			<y43>503</y43>
			<x44>335</x44>
			<y44>426</y44>
			<x45>385</x45>
			<y45>375</y45>
			<x46>379</x46>
			<y46>319</y46>
		</polygon>
</object>
</annotation>
