<?xml version="1.0" ?>
<annotation>
<folder>data</folder>
<filename>frame-00578.jpg</filename>
<path>/Users/jason9075/Documents/Python/my_fcn/data/frame-00578.jpg</path>
<source>
    <database>Unknown</database>
</source>
<size>
    <width>720</width>
    <height>1280</height>
    <depth>3</depth>
</size>

<segmented>0</segmented>
    <object>
    <name>me</name>
    <pose>Unspecified</pose>
    <truncated>0</truncated>
    <difficult>0</difficult>
    <polygon>
			<x1>84</x1>
			<y1>183</y1>
			<x2>127</x2>
			<y2>172</y2>
			<x3>173</x3>
			<y3>183</y3>
			<x4>192</x4>
			<y4>234</y4>
			<x5>187</x5>
			<y5>267</y5>
			<x6>175</x6>
			<y6>305</y6>
			<x7>173</x7>
			<y7>329</y7>
			<x8>196</x8>
			<y8>354</y8>
			<x9>210</x9>
			<y9>416</y9>
			<x10>227</x10>
			<y10>464</y10>
			<x11>210</x11>
			<y11>478</y11>
			<x12>223</x12>
			<y12>540</y12>
			<x13>247</x13>
			<y13>592</y13>
			<x14>262</x14>
			<y14>652</y14>
			<x15>295</x15>
			<y15>722</y15>
			<x16>309</x16>
			<y16>759</y16>
			<x17>268</x17>
			<y17>767</y17>
			<x18>272</x18>
			<y18>726</y18>
			<x19>214</x19>
			<y19>608</y19>
			<x20>169</x20>
			<y20>501</y20>
			<x21>159</x21>
			<y21>569</y21>
			<x22>171</x22>
			<y22>680</y22>
			<x23>179</x23>
			<y23>779</y23>
			<x24>175</x24>
			<y24>951</y24>
			<x25>165</x25>
			<y25>965</y25>
			<x26>111</x26>
			<y26>951</y26>
			<x27>107</x27>
			<y27>994</y27>
			<x28>76</x28>
			<y28>1075</y28>
			<x29>63</x29>
			<y29>1122</y29>
			<x30>74</x30>
			<y30>1184</y30>
			<x31>82</x31>
			<y31>1211</y31>
			<x32>90</x32>
			<y32>1248</y32>
			<x33>113</x33>
			<y33>1265</y33>
			<x34>6</x34>
			<y34>1271</y34>
			<x35>-1</x35>
			<y35>344</y35>
			<x36>74</x36>
			<y36>290</y36>
			<x37>70</x37>
			<y37>249</y37>
			<x38>59</x38>
			<y38>216</y38>
		</polygon>
</object>
</annotation>
