<?xml version="1.0" ?>
<annotation>
<folder>data</folder>
<filename>frame-00824.jpg</filename>
<path>/Users/jason9075/Documents/Python/my_fcn/data/frame-00824.jpg</path>
<source>
    <database>Unknown</database>
</source>
<size>
    <width>720</width>
    <height>1280</height>
    <depth>3</depth>
</size>

<segmented>0</segmented>
    <object>
    <name>me</name>
    <pose>Unspecified</pose>
    <truncated>0</truncated>
    <difficult>0</difficult>
    <polygon>
			<x1>358</x1>
			<y1>440</y1>
			<x2>346</x2>
			<y2>469</y2>
			<x3>327</x3>
			<y3>505</y3>
			<x4>338</x4>
			<y4>527</y4>
			<x5>311</x5>
			<y5>544</y5>
			<x6>276</x6>
			<y6>579</y6>
			<x7>269</x7>
			<y7>600</y7>
			<x8>278</x8>
			<y8>633</y8>
			<x9>272</x9>
			<y9>707</y9>
			<x10>284</x10>
			<y10>756</y10>
			<x11>300</x11>
			<y11>777</y11>
			<x12>298</x12>
			<y12>831</y12>
			<x13>323</x13>
			<y13>843</y13>
			<x14>325</x14>
			<y14>893</y14>
			<x15>329</x15>
			<y15>932</y15>
			<x16>327</x16>
			<y16>959</y16>
			<x17>315</x17>
			<y17>990</y17>
			<x18>338</x18>
			<y18>998</y18>
			<x19>352</x19>
			<y19>965</y19>
			<x20>348</x20>
			<y20>905</y20>
			<x21>356</x21>
			<y21>845</y21>
			<x22>383</x22>
			<y22>839</y22>
			<x23>389</x23>
			<y23>897</y23>
			<x24>381</x24>
			<y24>942</y24>
			<x25>387</x25>
			<y25>990</y25>
			<x26>389</x26>
			<y26>1014</y26>
			<x27>455</x27>
			<y27>1025</y27>
			<x28>447</x28>
			<y28>998</y28>
			<x29>418</x29>
			<y29>977</y29>
			<x30>426</x30>
			<y30>911</y30>
			<x31>428</x31>
			<y31>849</y31>
			<x32>428</x32>
			<y32>798</y32>
			<x33>426</x33>
			<y33>771</y33>
			<x34>443</x34>
			<y34>763</y34>
			<x35>441</x35>
			<y35>697</y35>
			<x36>433</x36>
			<y36>639</y36>
			<x37>431</x37>
			<y37>614</y37>
			<x38>447</x38>
			<y38>608</y38>
			<x39>428</x39>
			<y39>558</y39>
			<x40>402</x40>
			<y40>540</y40>
			<x41>395</x41>
			<y41>511</y41>
			<x42>404</x42>
			<y42>480</y42>
			<x43>377</x43>
			<y43>443</y43>
		</polygon>
</object>
</annotation>
